odoo10_addon_l10n_it_codici_carica-10.0.1.0.0-py2.7-nspkg.pth
odoo/addons/l10n_it_codici_carica/README.rst
odoo/addons/l10n_it_codici_carica/__init__.py
odoo/addons/l10n_it_codici_carica/__manifest__.py
odoo/addons/l10n_it_codici_carica/data/codici_carica_data.xml
odoo/addons/l10n_it_codici_carica/i18n/it.po
odoo/addons/l10n_it_codici_carica/models/__init__.py
odoo/addons/l10n_it_codici_carica/models/codice_carica.py
odoo/addons/l10n_it_codici_carica/security/ir.model.access.csv
odoo/addons/l10n_it_codici_carica/views/codice_carica_view.xml
odoo10_addon_l10n_it_codici_carica-10.0.1.0.0.dist-info/DESCRIPTION.rst
odoo10_addon_l10n_it_codici_carica-10.0.1.0.0.dist-info/METADATA
odoo10_addon_l10n_it_codici_carica-10.0.1.0.0.dist-info/RECORD
odoo10_addon_l10n_it_codici_carica-10.0.1.0.0.dist-info/WHEEL
odoo10_addon_l10n_it_codici_carica-10.0.1.0.0.dist-info/metadata.json
odoo10_addon_l10n_it_codici_carica-10.0.1.0.0.dist-info/namespace_packages.txt
odoo10_addon_l10n_it_codici_carica-10.0.1.0.0.dist-info/top_level.txt
