Metadata-Version: 2.0
Name: odoo10-addon-l10n-it-codici-carica
Version: 10.0.1.0.0
Summary: Aggiunge la tabella dei codici carica da usare nei dichiarativi fiscali italiani
Home-page: http://odoo-italia.net
Author: Openforce di Camilli Alessandro,Odoo Community Association (OCA)
Author-email: support@odoo-community.org
License: LGPL-3
Platform: UNKNOWN
Classifier: Programming Language :: Python :: 2.7
Classifier: Framework :: Odoo
Classifier: License :: OSI Approved :: GNU Lesser General Public License v3 (LGPLv3)
Requires-Dist: odoo (<10.1dev,>=10.0)
